{
  "users": [
    {
      "id": 1,
      "name": "ghada",
      "email": "ghada@teacher.com",
      "isTeacher": 1,
      "password": "12345"
    },
    {
      "id": 1,
      "name": "ahmed",
      "email": "ahmed@student.com",
      "isTeacher": 0,
      "password": "12345"
    }
  ],
  "quizs": [
    {
      "id": 4,
      "quizTitle": "test quiz for save ",
      "questions": [
        {
          "title": "test",
          "correctAnswer": "test",
          "possibleAnswers": [
            "test",
            "test",
            "test",
            "test"
          ],
          "explanation": "test",
          "Id": 1
        }
      ],
      "teacherId": 1,
      "saved": 0,
      "published": 1
    },
    {
      "id": 6,
      "quizTitle": "test quiz for save ",
      "questions": [
        {
          "title": "test",
          "correctAnswer": "test",
          "possibleAnswers": [
            "test",
            "test",
            "test",
            "test"
          ],
          "explanation": "test",
          "Id": 1
        }
      ],
      "teacherId": 1,
      "saved": 1,
      "published": 0
    },
    {
      "id": 7,
      "quizTitle": "test quiz for save ",
      "questions": [
        {
          "title": "test",
          "correctAnswer": "test",
          "possibleAnswers": [
            "test",
            "test",
            "test",
            "test"
          ],
          "explanation": "test",
          "Id": 1
        }
      ],
      "teacherId": 1,
      "saved": 1,
      "published": 0
    },
    {
      "id": 8,
      "quizTitle": "test quiz for save ",
      "questions": [
        {
          "title": "test",
          "correctAnswer": "test",
          "possibleAnswers": [
            "test",
            "test",
            "test",
            "test"
          ],
          "explanation": "test",
          "Id": 1
        }
      ],
      "teacherId": 1,
      "saved": 0,
      "published": 1
    },
    {
      "id": 5,
      "quizTitle": "u",
      "questions": [
        {
          "title": "otti",
          "correctAnswer": "o",
          "possibleAnswers": [
            "o",
            "o",
            "oo",
            "o"
          ],
          "explanation": "o",
          "Id": 1
        }
      ],
      "teacherId": 1,
      "saved": 1,
      "published": 0
    }
  ]
}